zeroeval/__init__.py
zeroeval/cache.py
zeroeval/client.py
zeroeval/errors.py
zeroeval/providers.py
zeroeval/pyproject.toml
zeroeval/template.py
zeroeval/types.py
zeroeval/cli/__init__.py
zeroeval/cli/main.py
zeroeval/cli/runner.py
zeroeval/cli/setup.py
zeroeval/cli/utils.py
zeroeval/core/__init__.py
zeroeval/core/dataset_class.py
zeroeval/core/decorators.py
zeroeval/core/evaluation.py
zeroeval/core/evaluator_class.py
zeroeval/core/experiment_class.py
zeroeval/core/init.py
zeroeval/core/metrics.py
zeroeval/core/reader.py
zeroeval/core/run.py
zeroeval/core/run_collection.py
zeroeval/core/task.py
zeroeval/core/writer.py
zeroeval/observability/__init__.py
zeroeval/observability/choice.py
zeroeval/observability/decorators.py
zeroeval/observability/signals.py
zeroeval/observability/span.py
zeroeval/observability/tracer.py
zeroeval/observability/utils.py
zeroeval/observability/writer.py
zeroeval/observability/integrations/__init__.py
zeroeval/observability/integrations/base.py
zeroeval/observability/integrations/registry.py
zeroeval/observability/integrations/utils.py
zeroeval/observability/integrations/gemini/__init__.py
zeroeval/observability/integrations/gemini/integration.py
zeroeval/observability/integrations/httpx/README.md
zeroeval/observability/integrations/httpx/__init__.py
zeroeval/observability/integrations/httpx/integration.py
zeroeval/observability/integrations/langchain/__init__.py
zeroeval/observability/integrations/langchain/integration.py
zeroeval/observability/integrations/langgraph/integration.py
zeroeval/observability/integrations/openai/__init__.py
zeroeval/observability/integrations/openai/integration.py
zeroeval/observability/integrations/vocode/__init__.py
zeroeval/observability/integrations/vocode/integration.py
zeroeval/observability/integrations/vocode/streaming_tracker.py
zeroeval/utils/hash.py
zeroeval-0.6.121.dist-info/METADATA
zeroeval-0.6.121.dist-info/WHEEL
zeroeval-0.6.121.dist-info/entry_points.txt
zeroeval-0.6.121.dist-info/RECORD
