Metadata-Version: 2.4
Name: zeroeval
Version: 0.6.121
Summary: ZeroEval SDK
Project-URL: Repository, https://github.com/zeroeval
Author-email: Sebastian Crossa <seb@zeroeval.com>, Jonathan Chavez <jona@zeroeval.com>
Keywords: LLM,evaluation,observability
Requires-Python: <4.0,>=3.9
Requires-Dist: opentelemetry-api>=1.26.0
Requires-Dist: opentelemetry-exporter-otlp-proto-http>=1.26.0
Requires-Dist: opentelemetry-sdk>=1.26.0
Requires-Dist: python-dotenv>=1.0.0
Requires-Dist: requests>=2.32.2
Requires-Dist: rich>=13.7.1
Provides-Extra: all
Requires-Dist: google-genai>=1.21.1; extra == 'all'
Requires-Dist: langchain-core>=0.1.0; extra == 'all'
Requires-Dist: langgraph>=0.0.20; extra == 'all'
Requires-Dist: openai>=1.59.6; extra == 'all'
Provides-Extra: gemini
Requires-Dist: google-genai>=1.21.1; extra == 'gemini'
Provides-Extra: langchain
Requires-Dist: langchain-core>=0.1.0; extra == 'langchain'
Provides-Extra: langgraph
Requires-Dist: langgraph>=0.0.20; extra == 'langgraph'
Provides-Extra: openai
Requires-Dist: openai>=1.59.6; extra == 'openai'
